j2_template/__init__.py
j2_template/__version__.py
j2_template/cli.py
j2_template/core.py
test/__init__.py
test/demo1.py
j2_template-1.3.0.dist-info/LICENSE
j2_template-1.3.0.dist-info/METADATA
j2_template-1.3.0.dist-info/WHEEL
j2_template-1.3.0.dist-info/entry_points.txt
j2_template-1.3.0.dist-info/top_level.txt
j2_template-1.3.0.dist-info/RECORD
