Metadata-Version: 2.1
Name: j2-template
Version: 1.3.0
Summary: A Python package for generating Jinja2 templates
Home-page: https://github.com/me/myproject
Author: hu jianli
Author-email: me@example.com
License: MIT
Platform: UNKNOWN
Classifier: License :: OSI Approved :: MIT License
Classifier: Programming Language :: Python
Classifier: Programming Language :: Python :: 3
Classifier: Programming Language :: Python :: 3.6
Classifier: Programming Language :: Python :: Implementation :: CPython
Classifier: Programming Language :: Python :: Implementation :: PyPy
Requires-Python: >=3.6.0
Requires-Dist: jinja2
